remote_debug/__init__.py
remote_debug/cli.py
remote_debug-0.2.9.dist-info/licenses/LICENSE
remote_debug-0.2.9.dist-info/METADATA
remote_debug-0.2.9.dist-info/WHEEL
remote_debug-0.2.9.dist-info/entry_points.txt
remote_debug-0.2.9.dist-info/top_level.txt
remote_debug-0.2.9.dist-info/RECORD
