Metadata-Version: 2.4
Name: remote-debug
Version: 0.2.9
Summary: A helper tool for remote debugging on HPC clusters.
Author-email: Paul Link <paul.link@student.kit.edu>
License: MIT
Requires-Python: >=3.8
License-File: LICENSE
Requires-Dist: rich-click
Requires-Dist: debugpy
Dynamic: license-file
